LICENSE
MANIFEST.in
README.md
package.json
setup.py
../README.md
dash_datetimepicker/DashDatetimepicker.py
dash_datetimepicker/DashDatetimepickerSingle.py
dash_datetimepicker/__init__.py
dash_datetimepicker/_imports_.py
dash_datetimepicker/dash_datetimepicker.css
dash_datetimepicker/dash_datetimepicker.min.js
dash_datetimepicker/dash_datetimepicker.min.js.map
dash_datetimepicker/metadata.json
dash_datetimepicker/package-info.json
dash_datetimepicker.egg-info/PKG-INFO
dash_datetimepicker.egg-info/SOURCES.txt
dash_datetimepicker.egg-info/dependency_links.txt
dash_datetimepicker.egg-info/top_level.txt