Metadata-Version: 2.1
Name: dash-datetimepicker
Version: 0.0.7
Summary: Dash component to select date and times
Home-page: UNKNOWN
Author: Sebastian Rehfeldt <sebastian.rehfeldt@gmx.net>
License: MIT
Platform: UNKNOWN
Classifier: Framework :: Dash
License-File: LICENSE
